truefoundry/__init__.py
truefoundry/_client.py
truefoundry/logger.py
truefoundry/pydantic_v1.py
truefoundry/version.py
truefoundry/autodeploy/__init__.py
truefoundry/autodeploy/cli.py
truefoundry/autodeploy/constants.py
truefoundry/autodeploy/exception.py
truefoundry/autodeploy/logger.py
truefoundry/autodeploy/agents/__init__.py
truefoundry/autodeploy/agents/base.py
truefoundry/autodeploy/agents/developer.py
truefoundry/autodeploy/agents/project_identifier.py
truefoundry/autodeploy/agents/tester.py
truefoundry/autodeploy/tools/__init__.py
truefoundry/autodeploy/tools/ask.py
truefoundry/autodeploy/tools/base.py
truefoundry/autodeploy/tools/commit.py
truefoundry/autodeploy/tools/docker_build.py
truefoundry/autodeploy/tools/docker_run.py
truefoundry/autodeploy/tools/file_type_counts.py
truefoundry/autodeploy/tools/list_files.py
truefoundry/autodeploy/tools/read_file.py
truefoundry/autodeploy/tools/send_request.py
truefoundry/autodeploy/tools/write_file.py
truefoundry/autodeploy/utils/client.py
truefoundry/autodeploy/utils/diff.py
truefoundry/autodeploy/utils/pydantic_compat.py
truefoundry/cli/__init__.py
truefoundry/cli/__main__.py
truefoundry/cli/config.py
truefoundry/cli/console.py
truefoundry/cli/const.py
truefoundry/cli/display_util.py
truefoundry/cli/util.py
truefoundry/common/__init__.py
truefoundry/common/auth_service_client.py
truefoundry/common/constants.py
truefoundry/common/credential_file_manager.py
truefoundry/common/credential_provider.py
truefoundry/common/entities.py
truefoundry/common/exceptions.py
truefoundry/common/request_utils.py
truefoundry/common/servicefoundry_client.py
truefoundry/common/session.py
truefoundry/common/storage_provider_utils.py
truefoundry/common/types.py
truefoundry/common/utils.py
truefoundry/common/warnings.py
truefoundry/deploy/__init__.py
truefoundry/deploy/python_deploy_codegen.py
truefoundry/deploy/_autogen/models.py
truefoundry/deploy/builder/__init__.py
truefoundry/deploy/builder/constants.py
truefoundry-0.13.12.dist-info/METADATA
truefoundry-0.13.12.dist-info/WHEEL
truefoundry-0.13.12.dist-info/entry_points.txt
truefoundry-0.13.12.dist-info/RECORD
