Metadata-Version: 2.4
Name: truefoundry
Version: 0.13.12
Summary: TrueFoundry CLI
Author-email: TrueFoundry Team <abhishek@truefoundry.com>
Requires-Python: <3.15,>=3.8.1
Requires-Dist: aenum<4.0.0,>=3.0.0
Requires-Dist: click<9.0.0,>=7.0.0
Requires-Dist: coolname<2.0.0,>=1.1.0
Requires-Dist: docker<8.0.0,>=6.1.2
Requires-Dist: filelock<4.0.0,>=3.8.0
Requires-Dist: gitignorefile<2.0.0,>=1.1.2
Requires-Dist: gitpython<4.0.0,>=3.1.43
Requires-Dist: importlib-metadata<9.0.0,>=4.11.3
Requires-Dist: importlib-resources<7.0.0,>=5.2.0
Requires-Dist: jinja2<4.0.0,>=3.1.6
Requires-Dist: mako<2.0.0,>=1.1.6
Requires-Dist: numpy<3.0.0,>=1.23.0
Requires-Dist: openai<2.0.0,>=1.16.2
Requires-Dist: packaging<26.0,>=20.0
Requires-Dist: pydantic<3.0.0,>=1.8.2
Requires-Dist: pygments<3.0.0,>=2.12.0
Requires-Dist: pyjwt<3.0.0,>=2.0.0
Requires-Dist: python-dateutil<3.0.0,>=2.8.2
Requires-Dist: python-dotenv<2.0.0,>=1.0.1
Requires-Dist: python-socketio[client]<6.0.0,>=5.5.2
Requires-Dist: pyyaml<7.0.0,>=6.0.0
Requires-Dist: questionary<2.0.0,>=1.10.0
Requires-Dist: requests<3.0.0,>=2.18.0
Requires-Dist: requirements-parser<0.12.0,>=0.11.0
Requires-Dist: rich-click<2.0.0,>=1.2.1
Requires-Dist: rich<14.0.0,>=13.7.1
Requires-Dist: tqdm<5.0.0,>=4.0.0
Requires-Dist: truefoundry-sdk<0.2.0,>=0.1.19
Requires-Dist: typing-extensions>=4.0
Requires-Dist: urllib3<3,>=1.26.18
Requires-Dist: yq<4.0.0,>=3.1.0
Provides-Extra: spark
Requires-Dist: flytekit==1.15.3; (python_version >= '3.9' and python_version <= '3.12') and extra == 'spark'
Requires-Dist: flytekitplugins-spark==1.15.3; (python_version >= '3.9' and python_version <= '3.12') and extra == 'spark'
Provides-Extra: workflow
Requires-Dist: flytekit==1.15.3; (python_version >= '3.9' and python_version <= '3.12') and extra == 'workflow'
